[
  {
    "id": 1,
    "foodname": "Margherita Pizza",
    "restaurantName": "Spice Hub",
    "category": "Italian",
    "address": "1 Food Street",
    "location": "Delhi",
    "state": "Delhi",
    "rating": 3.5,
    "price": 100,
    "imageurl": "https://source.unsplash.com/400x300/?food,Margherita%20Pizza"
  },
  {
    "id": 2,
    "foodname": "Chicken Biryani",
    "restaurantName": "Foodie Stop",
    "category": "Chinese",
    "address": "2 Food Street",
    "location": "Mumbai",
    "state": "Maharashtra",
    "rating": 3.8,
    "price": 110,
    "imageurl": "https://source.unsplash.com/400x300/?food,Chicken%20Biryani"
  },
  {
    "id": 3,
    "foodname": "Paneer Tikka",
    "restaurantName": "Tandoori Tales",
    "category": "Indian",
    "address": "3 Food Street",
    "location": "Bangalore",
    "state": "Karnataka",
    "rating": 4.1,
    "price": 120,
    "imageurl": "https://source.unsplash.com/400x300/?food,Paneer%20Tikka"
  },
  {
    "id": 4,
    "foodname": "Sushi Platter",
    "restaurantName": "Pasta Palace",
    "category": "Mexican",
    "address": "4 Food Street",
    "location": "Hyderabad",
    "state": "Telangana",
    "rating": 4.4,
    "price": 130,
    "imageurl": "https://source.unsplash.com/400x300/?food,Sushi%20Platter"
  },
  {
    "id": 5,
    "foodname": "Chow Mein",
    "restaurantName": "Sushi Central",
    "category": "Thai",
    "address": "5 Food Street",
    "location": "Chennai",
    "state": "Tamil Nadu",
    "rating": 4.7,
    "price": 140,
    "imageurl": "https://source.unsplash.com/400x300/?food,Chow%20Mein"
  },
  {
    "id": 6,
    "foodname": "Tacos",
    "restaurantName": "Biryani House",
    "category": "Continental",
    "address": "6 Food Street",
    "location": "Kolkata",
    "state": "West Bengal",
    "rating": 3.5,
    "price": 150,
    "imageurl": "https://source.unsplash.com/400x300/?food,Tacos"
  },
  {
    "id": 7,
    "foodname": "Butter Chicken",
    "restaurantName": "Urban Tadka",
    "category": "Japanese",
    "address": "7 Food Street",
    "location": "Pune",
    "state": "Maharashtra",
    "rating": 3.8,
    "price": 160,
    "imageurl": "https://source.unsplash.com/400x300/?food,Butter%20Chicken"
  },
  {
    "id": 8,
    "foodname": "Veg Manchurian",
    "restaurantName": "Spice Hub",
    "category": "Italian",
    "address": "8 Food Street",
    "location": "Ahmedabad",
    "state": "Gujarat",
    "rating": 4.1,
    "price": 170,
    "imageurl": "https://source.unsplash.com/400x300/?food,Veg%20Manchurian"
  },
  {
    "id": 9,
    "foodname": "Momos",
    "restaurantName": "Foodie Stop",
    "category": "Chinese",
    "address": "9 Food Street",
    "location": "Jaipur",
    "state": "Rajasthan",
    "rating": 4.4,
    "price": 180,
    "imageurl": "https://source.unsplash.com/400x300/?food,Momos"
  },
  {
    "id": 10,
    "foodname": "Lasagna",
    "restaurantName": "Tandoori Tales",
    "category": "Indian",
    "address": "10 Food Street",
    "location": "Lucknow",
    "state": "Uttar Pradesh",
    "rating": 4.7,
    "price": 190,
    "imageurl": "https://source.unsplash.com/400x300/?food,Lasagna"
  },
  {
    "id": 11,
    "foodname": "Ramen",
    "restaurantName": "Pasta Palace",
    "category": "Mexican",
    "address": "11 Food Street",
    "location": "Delhi",
    "state": "Delhi",
    "rating": 3.5,
    "price": 200,
    "imageurl": "https://source.unsplash.com/400x300/?food,Ramen"
  },
  {
    "id": 12,
    "foodname": "Spring Rolls",
    "restaurantName": "Sushi Central",
    "category": "Thai",
    "address": "12 Food Street",
    "location": "Mumbai",
    "state": "Maharashtra",
    "rating": 3.8,
    "price": 210,
    "imageurl": "https://source.unsplash.com/400x300/?food,Spring%20Rolls"
  },
  {
    "id": 13,
    "foodname": "Nachos",
    "restaurantName": "Biryani House",
    "category": "Continental",
    "address": "13 Food Street",
    "location": "Bangalore",
    "state": "Karnataka",
    "rating": 4.1,
    "price": 220,
    "imageurl": "https://source.unsplash.com/400x300/?food,Nachos"
  },
  {
    "id": 14,
    "foodname": "Palak Paneer",
    "restaurantName": "Urban Tadka",
    "category": "Japanese",
    "address": "14 Food Street",
    "location": "Hyderabad",
    "state": "Telangana",
    "rating": 4.4,
    "price": 230,
    "imageurl": "https://source.unsplash.com/400x300/?food,Palak%20Paneer"
  },
  {
    "id": 15,
    "foodname": "Grilled Sandwich",
    "restaurantName": "Spice Hub",
    "category": "Italian",
    "address": "15 Food Street",
    "location": "Chennai",
    "state": "Tamil Nadu",
    "rating": 4.7,
    "price": 240,
    "imageurl": "https://source.unsplash.com/400x300/?food,Grilled%20Sandwich"
  },
  {
    "id": 16,
    "foodname": "Kathi Roll",
    "restaurantName": "Foodie Stop",
    "category": "Chinese",
    "address": "16 Food Street",
    "location": "Kolkata",
    "state": "West Bengal",
    "rating": 3.5,
    "price": 250,
    "imageurl": "https://source.unsplash.com/400x300/?food,Kathi%20Roll"
  },
  {
    "id": 17,
    "foodname": "Dal Makhani",
    "restaurantName": "Tandoori Tales",
    "category": "Indian",
    "address": "17 Food Street",
    "location": "Pune",
    "state": "Maharashtra",
    "rating": 3.8,
    "price": 260,
    "imageurl": "https://source.unsplash.com/400x300/?food,Dal%20Makhani"
  },
  {
    "id": 18,
    "foodname": "Fried Rice",
    "restaurantName": "Pasta Palace",
    "category": "Mexican",
    "address": "18 Food Street",
    "location": "Ahmedabad",
    "state": "Gujarat",
    "rating": 4.1,
    "price": 270,
    "imageurl": "https://source.unsplash.com/400x300/?food,Fried%20Rice"
  },
  {
    "id": 19,
    "foodname": "Chilli Chicken",
    "restaurantName": "Sushi Central",
    "category": "Thai",
    "address": "19 Food Street",
    "location": "Jaipur",
    "state": "Rajasthan",
    "rating": 4.4,
    "price": 280,
    "imageurl": "https://source.unsplash.com/400x300/?food,Chilli%20Chicken"
  },
  {
    "id": 20,
    "foodname": "Masala Dosa",
    "restaurantName": "Biryani House",
    "category": "Continental",
    "address": "20 Food Street",
    "location": "Lucknow",
    "state": "Uttar Pradesh",
    "rating": 4.7,
    "price": 290,
    "imageurl": "https://source.unsplash.com/400x300/?food,Masala%20Dosa"
  },
  {
    "id": 21,
    "foodname": "Idli Sambhar",
    "restaurantName": "Urban Tadka",
    "category": "Japanese",
    "address": "21 Food Street",
    "location": "Delhi",
    "state": "Delhi",
    "rating": 3.5,
    "price": 100,
    "imageurl": "https://source.unsplash.com/400x300/?food,Idli%20Sambhar"
  },
  {
    "id": 22,
    "foodname": "Vada Pav",
    "restaurantName": "Spice Hub",
    "category": "Italian",
    "address": "22 Food Street",
    "location": "Mumbai",
    "state": "Maharashtra",
    "rating": 3.8,
    "price": 110,
    "imageurl": "https://source.unsplash.com/400x300/?food,Vada%20Pav"
  },
  {
    "id": 23,
    "foodname": "Poha",
    "restaurantName": "Foodie Stop",
    "category": "Chinese",
    "address": "23 Food Street",
    "location": "Bangalore",
    "state": "Karnataka",
    "rating": 4.1,
    "price": 120,
    "imageurl": "https://source.unsplash.com/400x300/?food,Poha"
  },
  {
    "id": 24,
    "foodname": "Aloo Paratha",
    "restaurantName": "Tandoori Tales",
    "category": "Indian",
    "address": "24 Food Street",
    "location": "Hyderabad",
    "state": "Telangana",
    "rating": 4.4,
    "price": 130,
    "imageurl": "https://source.unsplash.com/400x300/?food,Aloo%20Paratha"
  },
  {
    "id": 25,
    "foodname": "Gulab Jamun",
    "restaurantName": "Pasta Palace",
    "category": "Mexican",
    "address": "25 Food Street",
    "location": "Chennai",
    "state": "Tamil Nadu",
    "rating": 4.7,
    "price": 140,
    "imageurl": "https://source.unsplash.com/400x300/?food,Gulab%20Jamun"
  },
  {
    "id": 26,
    "foodname": "Jalebi",
    "restaurantName": "Sushi Central",
    "category": "Thai",
    "address": "26 Food Street",
    "location": "Kolkata",
    "state": "West Bengal",
    "rating": 3.5,
    "price": 150,
    "imageurl": "https://source.unsplash.com/400x300/?food,Jalebi"
  },
  {
    "id": 27,
    "foodname": "Pav Bhaji",
    "restaurantName": "Biryani House",
    "category": "Continental",
    "address": "27 Food Street",
    "location": "Pune",
    "state": "Maharashtra",
    "rating": 3.8,
    "price": 160,
    "imageurl": "https://source.unsplash.com/400x300/?food,Pav%20Bhaji"
  },
  {
    "id": 28,
    "foodname": "Kebabs",
    "restaurantName": "Urban Tadka",
    "category": "Japanese",
    "address": "28 Food Street",
    "location": "Ahmedabad",
    "state": "Gujarat",
    "rating": 4.1,
    "price": 170,
    "imageurl": "https://source.unsplash.com/400x300/?food,Kebabs"
  },
  {
    "id": 29,
    "foodname": "Hakka Noodles",
    "restaurantName": "Spice Hub",
    "category": "Italian",
    "address": "29 Food Street",
    "location": "Jaipur",
    "state": "Rajasthan",
    "rating": 4.4,
    "price": 180,
    "imageurl": "https://source.unsplash.com/400x300/?food,Hakka%20Noodles"
  },
  {
    "id": 30,
    "foodname": "Pizza Burger",
    "restaurantName": "Foodie Stop",
    "category": "Chinese",
    "address": "30 Food Street",
    "location": "Lucknow",
    "state": "Uttar Pradesh",
    "rating": 4.7,
    "price": 190,
    "imageurl": "https://source.unsplash.com/400x300/?food,Pizza%20Burger"
  },
  {
    "id": 31,
    "foodname": "Garlic Bread",
    "restaurantName": "Tandoori Tales",
    "category": "Indian",
    "address": "31 Food Street",
    "location": "Delhi",
    "state": "Delhi",
    "rating": 3.5,
    "price": 200,
    "imageurl": "https://source.unsplash.com/400x300/?food,Garlic%20Bread"
  },
  {
    "id": 32,
    "foodname": "Schezwan Rice",
    "restaurantName": "Pasta Palace",
    "category": "Mexican",
    "address": "32 Food Street",
    "location": "Mumbai",
    "state": "Maharashtra",
    "rating": 3.8,
    "price": 210,
    "imageurl": "https://source.unsplash.com/400x300/?food,Schezwan%20Rice"
  },
  {
    "id": 33,
    "foodname": "Rajma Chawal",
    "restaurantName": "Sushi Central",
    "category": "Thai",
    "address": "33 Food Street",
    "location": "Bangalore",
    "state": "Karnataka",
    "rating": 4.1,
    "price": 220,
    "imageurl": "https://source.unsplash.com/400x300/?food,Rajma%20Chawal"
  },
  {
    "id": 34,
    "foodname": "Chole Bhature",
    "restaurantName": "Biryani House",
    "category": "Continental",
    "address": "34 Food Street",
    "location": "Hyderabad",
    "state": "Telangana",
    "rating": 4.4,
    "price": 230,
    "imageurl": "https://source.unsplash.com/400x300/?food,Chole%20Bhature"
  },
  {
    "id": 35,
    "foodname": "Fish Curry",
    "restaurantName": "Urban Tadka",
    "category": "Japanese",
    "address": "35 Food Street",
    "location": "Chennai",
    "state": "Tamil Nadu",
    "rating": 4.7,
    "price": 240,
    "imageurl": "https://source.unsplash.com/400x300/?food,Fish%20Curry"
  },
  {
    "id": 36,
    "foodname": "Egg Curry",
    "restaurantName": "Spice Hub",
    "category": "Italian",
    "address": "36 Food Street",
    "location": "Kolkata",
    "state": "West Bengal",
    "rating": 3.5,
    "price": 250,
    "imageurl": "https://source.unsplash.com/400x300/?food,Egg%20Curry"
  },
  {
    "id": 37,
    "foodname": "Tandoori Roti",
    "restaurantName": "Foodie Stop",
    "category": "Chinese",
    "address": "37 Food Street",
    "location": "Pune",
    "state": "Maharashtra",
    "rating": 3.8,
    "price": 260,
    "imageurl": "https://source.unsplash.com/400x300/?food,Tandoori%20Roti"
  },
  {
    "id": 38,
    "foodname": "Naan",
    "restaurantName": "Tandoori Tales",
    "category": "Indian",
    "address": "38 Food Street",
    "location": "Ahmedabad",
    "state": "Gujarat",
    "rating": 4.1,
    "price": 270,
    "imageurl": "https://source.unsplash.com/400x300/?food,Naan"
  },
  {
    "id": 39,
    "foodname": "Chicken 65",
    "restaurantName": "Pasta Palace",
    "category": "Mexican",
    "address": "39 Food Street",
    "location": "Jaipur",
    "state": "Rajasthan",
    "rating": 4.4,
    "price": 280,
    "imageurl": "https://source.unsplash.com/400x300/?food,Chicken%2065"
  },
  {
    "id": 40,
    "foodname": "Malai Kofta",
    "restaurantName": "Sushi Central",
    "category": "Thai",
    "address": "40 Food Street",
    "location": "Lucknow",
    "state": "Uttar Pradesh",
    "rating": 4.7,
    "price": 290,
    "imageurl": "https://source.unsplash.com/400x300/?food,Malai%20Kofta"
  },
  {
    "id": 41,
    "foodname": "Gobi Manchurian",
    "restaurantName": "Biryani House",
    "category": "Continental",
    "address": "41 Food Street",
    "location": "Delhi",
    "state": "Delhi",
    "rating": 3.5,
    "price": 100,
    "imageurl": "https://source.unsplash.com/400x300/?food,Gobi%20Manchurian"
  },
  {
    "id": 42,
    "foodname": "Mutton Rogan Josh",
    "restaurantName": "Urban Tadka",
    "category": "Japanese",
    "address": "42 Food Street",
    "location": "Mumbai",
    "state": "Maharashtra",
    "rating": 3.8,
    "price": 110,
    "imageurl": "https://source.unsplash.com/400x300/?food,Mutton%20Rogan%20Josh"
  },
  {
    "id": 43,
    "foodname": "Dhokla",
    "restaurantName": "Spice Hub",
    "category": "Italian",
    "address": "43 Food Street",
    "location": "Bangalore",
    "state": "Karnataka",
    "rating": 4.1,
    "price": 120,
    "imageurl": "https://source.unsplash.com/400x300/?food,Dhokla"
  },
  {
    "id": 44,
    "foodname": "Thepla",
    "restaurantName": "Foodie Stop",
    "category": "Chinese",
    "address": "44 Food Street",
    "location": "Hyderabad",
    "state": "Telangana",
    "rating": 4.4,
    "price": 130,
    "imageurl": "https://source.unsplash.com/400x300/?food,Thepla"
  },
  {
    "id": 45,
    "foodname": "Sandwich Platter",
    "restaurantName": "Tandoori Tales",
    "category": "Indian",
    "address": "45 Food Street",
    "location": "Chennai",
    "state": "Tamil Nadu",
    "rating": 4.7,
    "price": 140,
    "imageurl": "https://source.unsplash.com/400x300/?food,Sandwich%20Platter"
  },
  {
    "id": 46,
    "foodname": "Cheese Burst Pizza",
    "restaurantName": "Pasta Palace",
    "category": "Mexican",
    "address": "46 Food Street",
    "location": "Kolkata",
    "state": "West Bengal",
    "rating": 3.5,
    "price": 150,
    "imageurl": "https://source.unsplash.com/400x300/?food,Cheese%20Burst%20Pizza"
  },
  {
    "id": 47,
    "foodname": "Corn Chaat",
    "restaurantName": "Sushi Central",
    "category": "Thai",
    "address": "47 Food Street",
    "location": "Pune",
    "state": "Maharashtra",
    "rating": 3.8,
    "price": 160,
    "imageurl": "https://source.unsplash.com/400x300/?food,Corn%20Chaat"
  },
  {
    "id": 48,
    "foodname": "Fruit Salad",
    "restaurantName": "Biryani House",
    "category": "Continental",
    "address": "48 Food Street",
    "location": "Ahmedabad",
    "state": "Gujarat",
    "rating": 4.1,
    "price": 170,
    "imageurl": "https://source.unsplash.com/400x300/?food,Fruit%20Salad"
  },
  {
    "id": 49,
    "foodname": "Ice Cream Sundae",
    "restaurantName": "Urban Tadka",
    "category": "Japanese",
    "address": "49 Food Street",
    "location": "Jaipur",
    "state": "Rajasthan",
    "rating": 4.4,
    "price": 180,
    "imageurl": "https://source.unsplash.com/400x300/?food,Ice%20Cream%20Sundae"
  },
  {
    "id": 50,
    "foodname": "Cold Coffee",
    "restaurantName": "Spice Hub",
    "category": "Italian",
    "address": "50 Food Street",
    "location": "Lucknow",
    "state": "Uttar Pradesh",
    "rating": 4.7,
    "price": 190,
    "imageurl": "https://source.unsplash.com/400x300/?food,Cold%20Coffee"
  }
]
